<?xml version="1.0" encoding="UTF-8"?>
<dictionary xmlns="http://marklogic.com/xdmp/spell">
  <metadata>
    <package-name>German spelling dictionary for use with MarkLogic Server</package-name>
    <date>2012-06-27</date>
    <version>0.60</version>
    <authors>
      <author>Greg Murray</author>
    </authors>
    <description>
      This dictionary is based on the GNU Aspell 0.60 German (Deutsches)
      Dictionary Package by Kevin Atkinson, based on a word list by Björn Jacke.
      See "sources" below for details. Greg Murray added XML tags to the word
      list to conform to the MarkLogic schema for spelling dictionaries.
    </description>
    <copyright>
      This document carries the same license and restrictions as the sources on
      which it is based. See "sources" below for details. Any reproduction or
      modification of all or part of the information contained in this document
      is governed by and must be accompanied by the attached license and
      copyright notices. Greg Murray makes no representations about the
      suitability of this document for any purpose. It is provided "as is"
      without express or implied warranty.
    </copyright>
    <sources>
      <source>
        <package-name>GNU Aspell 0.60 German (Deutsches) Dictionary Package</package-name>
        <date>2004-11-03</date>
        <version>0.60</version>
        <authors>
          <author>Kevin Atkinson</author>
        </authors>
        <copyright>
          GNU GENERAL PUBLIC LICENSE Version 2, June 1991
          
          Copyright 2000-2004 by Kevin Atkinson
          
          Permission to use, copy, modify, distribute and sell these word
          lists, the associated scripts, the output created from the scripts,
          and its documentation for any purpose is hereby granted without fee,
          provided that the above copyright notice appears in all copies and
          that both that copyright notice and this permission notice appear in
          supporting documentation. Kevin Atkinson makes no representations
          about the suitability of this array for any purpose. It is provided
          "as is" without express or implied warranty.
        </copyright>
        <sources>
          <source>
            <package-name>original German word list</package-name>
            <version>20030222-1</version>
            <authors>
              <author>Björn Jacke</author>
            </authors>
            <copyright>GNU GENERAL PUBLIC LICENSE Version 2, June 1991</copyright>
          </source>
        </sources>
      </source>
    </sources>
  </metadata>
  <word/>
  <word>ahoi</word>
  <word>AfA</word>
  <word>Hafer</word>
  <word>afferent</word>
  <word>afferenter</word>
  <word>afferente</word>
  <word>afferentes</word>
  <word>afferentem</word>
  <word>afferenten</word>
  <word>Afferenzen</word>
  <word>Haferflocken</word>
  <word>Avantgarde</word>
  <word>Avantgardefilme</word>
  <word>avantgardistisch</word>
  <word>avantgardistischer</word>
  <word>avantgardistische</word>
  <word>avantgardistisches</word>
  <word>avantgardistischem</word>
  <word>avantgardistischen</word>
  <word>Avantgarden</word>
  <word>Afferenz</word>
  <word>avanciere</word>
  <word>avancieren</word>
  <word>avancierend</word>
  <word>avancierender</word>
  <word>avancierende</word>
  <word>avancierendes</word>
  <word>avancierendem</word>
  <word>avancierenden</word>
  <word>avanciert</word>
  <word>avancierter</word>
  <word>avancierte</word>
  <word>avanciertet</word>
  <word>avanciertes</word>
  <word>avanciertest</word>
  <word>avanciertem</word>
  <word>avancierten</word>
  <word>avancierst</word>
  <word>Haferbrei</word>
  <word>Haferbreie</word>
  <word>Haferbreien</word>
  <word>Haferbreis</word>
  <word>Affäre</word>
  <word>Affären</word>
  <word>Havarie</word>
  <word>Havarien</word>
  <word>Hafers</word>
  <word>Aversion</word>
  <word>Aversionen</word>
  <word>Haferschleim</word>
  <word>Haferschleims</word>
  <word>Affe</word>
  <word>äffe</word>
  <word>Hawaii</word>
  <word>abpfeife</word>
  <word>abpfeifend</word>
  <word>abpfeifender</word>
  <word>abpfeifende</word>
  <word>abpfeifendes</word>
  <word>abpfeifendem</word>
  <word>abpfeifenden</word>
  <word>abpfeifen</word>
  <word>abpfeift</word>
  <word>abpfeifst</word>
  <word>Affekt</word>
  <word>Affekthandlung</word>
  <word>Affekthandlungen</word>
  <word>Affekte</word>
  <word>Affektes</word>
  <word>Affektivität</word>
  <word>affektiert</word>
